ansys/dpf/gatebin/_version.py
ansys/dpf/gatebin/libAns.Dpf.GrpcClient.so
ansys/dpf/gatebin/libDPFClientAPI.so
ansys_dpf_gatebin-0.4.1.dist-info/LICENSE
ansys_dpf_gatebin-0.4.1.dist-info/METADATA
ansys_dpf_gatebin-0.4.1.dist-info/WHEEL
ansys_dpf_gatebin-0.4.1.dist-info/top_level.txt
ansys_dpf_gatebin-0.4.1.dist-info/RECORD
